MANIFEST.in
README.rst
ez_setup.py
setup.cfg
setup.py
pyramid_genshi/__init__.py
pyramid_genshi.egg-info/PKG-INFO
pyramid_genshi.egg-info/SOURCES.txt
pyramid_genshi.egg-info/dependency_links.txt
pyramid_genshi.egg-info/not-zip-safe
pyramid_genshi.egg-info/requires.txt
pyramid_genshi.egg-info/top_level.txt
tests/__init__.py
tests/test_integration.py
tests/test_translation_string.py