Metadata-Version: 1.1
Name: pyramid-genshi
Version: 0.2.1
Summary: Genshi template bindings for the Pyramid web framework
Home-page: https://github.com/victorlin/pyramid_genshi
Author: Victor Lin
Author-email: bornstub@gmail.com
License: MIT
Keywords: bfg pyramid pylons genshi templates
Platform: UNKNOWN
Classifier: Intended Audience :: Developers
Classifier: Programming Language :: Python
Classifier: Topic :: Internet :: WWW/HTTP :: Dynamic Content
